topsis_saniya_102303183/__init__.py
topsis_saniya_102303183/topsis.py
topsis_saniya_102303183-1.0.5.dist-info/licenses/LICENSE
topsis_saniya_102303183-1.0.5.dist-info/METADATA
topsis_saniya_102303183-1.0.5.dist-info/WHEEL
topsis_saniya_102303183-1.0.5.dist-info/entry_points.txt
topsis_saniya_102303183-1.0.5.dist-info/top_level.txt
topsis_saniya_102303183-1.0.5.dist-info/RECORD
