Metadata-Version: 2.4
Name: Topsis-Saniya-102303183
Version: 1.0.5
Summary: TOPSIS implementation as a Python package
Author-email: Saniya <sjindal1_be23@thapar.edu>
License: MIT
Requires-Python: >=3.7
License-File: LICENSE
Requires-Dist: pandas
Requires-Dist: numpy
Dynamic: license-file
